LICENSE.txt
MANIFEST.in
README.rst
osaic.py
requirements.txt
setup.py
osaic.egg-info/PKG-INFO
osaic.egg-info/SOURCES.txt
osaic.egg-info/dependency_links.txt
osaic.egg-info/requires.txt
osaic.egg-info/top_level.txt
test/test_osaic.py