Metadata-Version: 1.1
Name: osaic
Version: 2.0.0
Summary: Create mosaics from images with ``python -mosaic image``
Home-page: https://bitbucket.org/iamFIREcracker/osaic
Author: Matteo Landi
Author-email: landimatte@gmail.com
License: BSD
Download-URL: http://pypi.python.org/pypi/osaic
Keywords: photo,image,mosaic,creator
Platform: UNKNOWN
Classifier: Development Status :: 5 - Production/Stable
Classifier: Environment :: Console
Classifier: Intended Audience :: Developers
Classifier: License :: OSI Approved :: BSD License
Classifier: Operating System :: OS Independent
Classifier: Programming Language :: Python
Classifier: Programming Language :: Python :: 2.5
Classifier: Programming Language :: Python :: 2.6
Classifier: Topic :: Software Development :: Libraries :: Python Modules
Requires: PIL
Provides: osaic
